claude_proxy/__init__.py
claude_proxy/config.py
claude_proxy/main.py
claude_proxy/utils.py
claude_proxy/models/__init__.py
claude_proxy/models/claude.py
claude_proxy/models/openai.py
claude_proxy/providers/__init__.py
claude_proxy/providers/anthropic.py
claude_proxy/providers/base.py
claude_proxy/providers/openai.py
claude_proxy-0.8.0.dist-info/METADATA
claude_proxy-0.8.0.dist-info/WHEEL
claude_proxy-0.8.0.dist-info/entry_points.txt
claude_proxy-0.8.0.dist-info/licenses/LICENSE
claude_proxy-0.8.0.dist-info/RECORD
