Metadata-Version: 2.4
Name: claude-proxy
Version: 0.8.0
Summary: A production-ready Claude API proxy server
Author-email: simpx <simpxx@gmail.com>
License-File: LICENSE
Requires-Python: >=3.9
Requires-Dist: fastapi>=0.104.1
Requires-Dist: httpx>=0.25.0
Requires-Dist: pydantic-settings>=2.0.0
Requires-Dist: pydantic>=2.5.0
Requires-Dist: python-dotenv>=1.0.0
Requires-Dist: uvicorn[standard]>=0.24.0
Provides-Extra: dev
Requires-Dist: anthropic>=0.34.0; extra == 'dev'
Requires-Dist: black>=23.10.0; extra == 'dev'
Requires-Dist: mypy>=1.7.0; extra == 'dev'
Requires-Dist: pytest-asyncio>=0.21.0; extra == 'dev'
Requires-Dist: pytest>=7.4.0; extra == 'dev'
Requires-Dist: ruff>=0.1.4; extra == 'dev'
Provides-Extra: production
Requires-Dist: gunicorn>=21.0.0; extra == 'production'
